{"title":"The Core 2003 BluRay 720p DTS x264-3Li","uid":7992484,"size":5953677350,"categoryP":"video","categoryS":"hd___movies","magnet":"?xt=urn:btih:084870e98bef6c10c2ec4694c16b676067c2bfee&amp;dn=The+Core+2003+BluRay+720p+DTS+x264-3Li&amp;tr=udp%3A%2F%2Ftracker.openbittorrent.com%3A80&amp;tr=udp%3A%2F%2Fopen.demonii.com%3A1337&amp;tr=udp%3A%2F%2Ftracker.coppersurfer.tk%3A6969&amp;tr=udp%3A%2F%2Fexodus.desync.com%3A6969","seeders":1,"leechers":1,"uploader":"3Li","files":-1,"time":1357524838,"description":"*Encoded/Released By.......: 3Li\n*Title/Year/Language.......: The Core/2003/English\n*Genre.....................: Action,Adventure,Sci-Fi,Thriller \n*Subtitles External(SubRip): Romanian,English (Hearing Impaired).\n*Subtitles External(VobSub): Danish,Dutch,English,Swedish.\n*Subtitles External(VobSub): English (Hearing Impaired),Finnish.\n*Subtitles External(VobSub): German,Norwegian,Spanish (Castilian).\n*Subtitles External(VobSub): French (Parisian).\n*Encoded/Profile/Level.....: 2 pass/High/Level 4.1\n*Codec/Writing Library.....: MPEG-4 AVC/H264/x264\n*Container.................: Mkv\n*Duration..................: 2h 14mn 57sec\n*Resolution................: 1280x544 pixels\n*File Size.................: 5.40 GB\n*Bit Rate..................: 4974 Kbps\n*Scan Type.................: Progressive\n*Bits/(Pixel*Frame)........: 0.298\n*Aspect Ratio/Frame Rate...: 2.35:1/23.976 fps\n*Stream Video Size.........: 4.68 GB (87%)\n*Stream Audio Size.........: 728 MB (13%)\n*Audio Format/Bit Rate.....: DTS/755 Kbps\n*Bit Depth.................: 24 bits\n*Channel(s)/Sampling Rate..: 6 channels/48.0 KHz\n*Channel Positions.........: Front: L C R, Side: L R, LFE\n*Sample Video Runtime/Size.: 49sec/39 MB\n*Source/File Size..........: 1080p BluRay AVC DTS-HD MA 5.1 = 35.4 GB \n*Note: Make sure is a Real 3Li Release at ExtraTorrent\n*Thanks: ExtraTorrent,SaM...","torrent":{"xt":"urn:btih:084870e98bef6c10c2ec4694c16b676067c2bfee","amp;dn":"The+Core+2003+BluRay+720p+DTS+x264-3Li","amp;tr":["udp%3A%2F%2Ftracker.openbittorrent.com%3A80","udp%3A%2F%2Fopen.demonii.com%3A1337","udp%3A%2F%2Ftracker.coppersurfer.tk%3A6969","udp%3A%2F%2Fexodus.desync.com%3A6969"],"infoHash":"084870e98bef6c10c2ec4694c16b676067c2bfee","infoHashBuffer":{"type":"Buffer","data":[8,72,112,233,139,239,108,16,194,236,70,148,193,107,103,96,103,194,191,238]},"announce":[],"urlList":[]}}