{"title":"Massage Rooms - Uma And Micha HD 1080p","uid":8834729,"size":1545965389,"categoryP":"porn","categoryS":"hd___movies","magnet":"?xt=urn:btih:1da7fcc5e545efc37561060b87478962a2425d45&amp;dn=Massage+Rooms+-+Uma+And+Micha+HD+1080p&amp;tr=udp%3A%2F%2Ftracker.openbittorrent.com%3A80&amp;tr=udp%3A%2F%2Fopen.demonii.com%3A1337&amp;tr=udp%3A%2F%2Ftracker.coppersurfer.tk%3A6969&amp;tr=udp%3A%2F%2Fexodus.desync.com%3A6969","seeders":1,"leechers":1,"uploader":"ElitePorn","files":-1,"time":1377084979,"description":"Massage Rooms - Uma And Micha HD 1080p\n--------------------------------------\n\nScreenshots:\n------------\n &lt;a href=&quot;\nhttp://picturescream.asia/soft/JAu&quot; rel=&quot;nofollow&quot; target=&quot;_NEW&quot;&gt;\nhttp://picturescream.asia/soft/JAu&lt;/a&gt;\n &lt;a href=&quot;\nhttp://picturescream.asia/soft/JAv&quot; rel=&quot;nofollow&quot; target=&quot;_NEW&quot;&gt;\nhttp://picturescream.asia/soft/JAv&lt;/a&gt;\n &lt;a href=&quot;\nhttp://picturescream.asia/soft/JAM&quot; rel=&quot;nofollow&quot; target=&quot;_NEW&quot;&gt;\nhttp://picturescream.asia/soft/JAM&lt;/a&gt;\n &lt;a href=&quot;\nhttp://picturescream.asia/soft/JAP&quot; rel=&quot;nofollow&quot; target=&quot;_NEW&quot;&gt;\nhttp://picturescream.asia/soft/JAP&lt;/a&gt;\n &lt;a href=&quot;\nhttp://picturescream.asia/soft/JAm&quot; rel=&quot;nofollow&quot; target=&quot;_NEW&quot;&gt;\nhttp://picturescream.asia/soft/JAm&lt;/a&gt;\n &lt;a href=&quot;\nhttp://picturescream.asia/soft/JAw&quot; rel=&quot;nofollow&quot; target=&quot;_NEW&quot;&gt;\nhttp://picturescream.asia/soft/JAw&lt;/a&gt;\n\n\nDuration: 25:21, Format: MP4, Resolution: 1920x1080, Size: 1.440 GB","torrent":{"xt":"urn:btih:1da7fcc5e545efc37561060b87478962a2425d45","amp;dn":"Massage+Rooms+-+Uma+And+Micha+HD+1080p","amp;tr":["udp%3A%2F%2Ftracker.openbittorrent.com%3A80","udp%3A%2F%2Fopen.demonii.com%3A1337","udp%3A%2F%2Ftracker.coppersurfer.tk%3A6969","udp%3A%2F%2Fexodus.desync.com%3A6969"],"infoHash":"1da7fcc5e545efc37561060b87478962a2425d45","infoHashBuffer":{"type":"Buffer","data":[29,167,252,197,229,69,239,195,117,97,6,11,135,71,137,98,162,66,93,69]},"announce":[],"urlList":[]}}