{"title":"Superman Unbound 2013 576p WEB-DL x264 AAC-SSN","uid":8427937,"size":891303386,"categoryP":"video","categoryS":"tv_shows","magnet":"?xt=urn:btih:27ebb528bc38f0d332e990e7602e5155fdee2186&amp;dn=Superman+Unbound+2013+576p+WEB-DL+x264+AAC-SSN&amp;tr=udp%3A%2F%2Ftracker.openbittorrent.com%3A80&amp;tr=udp%3A%2F%2Fopen.demonii.com%3A1337&amp;tr=udp%3A%2F%2Ftracker.coppersurfer.tk%3A6969&amp;tr=udp%3A%2F%2Fexodus.desync.com%3A6969","seeders":1,"leechers":0,"uploader":"somespirit","files":2,"time":1367405892,"description":"\nIMDB: &lt;a href=&quot; http://www.imdb.com/title/tt2617456/&quot; rel=&quot;nofollow&quot; target=&quot;_NEW&quot;&gt; http://www.imdb.com/title/tt2617456/&lt;/a&gt;\n\n\n-[NoImage] x264 : frame I:1253  Avg QP:11.27  size: 58453\n-[NoImage] x264 : frame P:25375 Avg QP:13.51  size: 15105\n-[NoImage] x264 : frame B:81589 Avg QP:16.07  size:  3269\n-[NoImage] x264 : consecutive B-frames:  3.1%  4.0%  6.6% 44.4%  9.2% 10.4%  3.1% 10.0%  1.9%  3.7%  3.5%\nencoded 108217 frames, 137.23 fps, 1281.95 kb/s\n\n\n\n\n\nGeneral\nComplete name                            : Superman Unbound 2013 576p WEB-DL x264 AAC-SSN.mkv\nFormat                                   : Matroska\nFormat version                           : Version 4 / Version 2\nFile size                                : 850 MiB\nDuration                                 : 1h 15mn\nOverall bit rate                         : 1 580 Kbps\nEncoded date                             : UTC 2013-05-01 09:08:25\nWriting application                      : mkvmerge v6.2.0 ('Promised Land') built on Apr 28 2013 12:22:01\nWriting library                          : libebml v1.3.0 + libmatroska v1.4.0\n\nVideo\nID                                       : 1\nFormat                                   : AVC\nFormat/Info                              : Advanced Video Codec\nFormat profile                           : &lt;a class=&quot;__cf_email__&quot; href=&quot;/cdn-cgi/l/email-protection&quot; data-cfemail=&quot;1d55747a755d5129332c&quot;&gt;[email&amp;#160;protected]&lt;/a&gt;&lt;script data-cfhash='f9e31' type=&quot;text/javascript&quot;&gt;\n/* &lt;![CDATA[ */!function(){try{var t=&quot;currentScript&quot;in document?document.currentScript:function(){for(var t=document.getElementsByTagName(&quot;script&quot;),e=t.length;e--;)if(t[e].getAttribute(&quot;data-cfhash&quot;))return t[e]}();if(t&amp;&amp;t.previousSibling){var e,r,n,i,c=t.previousSibling,a=c.getAttribute(&quot;data-cfemail&quot;);if(a){for(e=&quot;&quot;,r=parseInt(a.substr(0,2),16),n=2;a.length-n;n+=2)i=parseInt(a.substr(n,2),16)^r,e+=String.fromCharCode(i);e=document.createTextNode(e),c.parentNode.replaceChild(e,c)}t.parentNode.removeChild(t);}}catch(u){}}()/* ]]&gt; */&lt;/script&gt;\nFormat settings, CABAC                   : Yes\nFormat settings, ReFrames                : 6 frames\nCodec ID                                 : V_MPEG4/ISO/AVC\nDuration                                 : 1h 15mn\nNominal bit rate                         : 1 281 Kbps\nWidth                                    : 1024 pixels\nHeight                                   : 574 pixels\nDisplay aspect ratio                     : 16:9\nOriginal display aspect ratio            : 16:9\nFrame rate mode                          : Constant\nFrame rate                               : 23.976 fps\nColor space                              : YUV\nChroma subsampling                       : 4:2:0\nBit depth                                : 8 bits\nScan type                                : Progressive\nBits/(Pixel*Frame)                       : 0.110\nWriting library                          : x264 core 132 r2309 3b1f1f7\nLanguage                                 : English\nDefault                                  : Yes\nForced                                   : No\n\nAudio\nID                                       : 2\nFormat                                   : AAC\nFormat/Info                              : Advanced Audio Codec\nFormat profile                           : LC\nCodec ID                                 : A_AAC\nDuration                                 : 1h 15mn\nChannel(s)                               : 6 channels\nChannel positions                        : Front: L C R, Side: L R, LFE\nSampling rate                            : 32.0 KHz\nCompression mode                         : Lossy\nDelay relative to video                  : 10ms\nDefault                                  : Yes\nForced                                   : No\n\n","torrent":{"xt":"urn:btih:27ebb528bc38f0d332e990e7602e5155fdee2186","amp;dn":"Superman+Unbound+2013+576p+WEB-DL+x264+AAC-SSN","amp;tr":["udp%3A%2F%2Ftracker.openbittorrent.com%3A80","udp%3A%2F%2Fopen.demonii.com%3A1337","udp%3A%2F%2Ftracker.coppersurfer.tk%3A6969","udp%3A%2F%2Fexodus.desync.com%3A6969"],"infoHash":"27ebb528bc38f0d332e990e7602e5155fdee2186","infoHashBuffer":{"type":"Buffer","data":[39,235,181,40,188,56,240,211,50,233,144,231,96,46,81,85,253,238,33,134]},"announce":[],"urlList":[]}}