{"title":"VA - All About The Drums (2012)","uid":8019107,"size":294037759,"categoryP":"audio","categoryS":"music","magnet":"?xt=urn:btih:32cc8ecffb4851d0c5f7c65033f183e97fe6fc8c&amp;dn=VA+-+All+About+The+Drums+%282012%29&amp;tr=udp%3A%2F%2Ftracker.openbittorrent.com%3A80&amp;tr=udp%3A%2F%2Fopen.demonii.com%3A1337&amp;tr=udp%3A%2F%2Ftracker.coppersurfer.tk%3A6969&amp;tr=udp%3A%2F%2Fexodus.desync.com%3A6969","seeders":1,"leechers":1,"uploader":"geloso","files":-1,"time":1358123243,"description":"Artist: VA\n\nTitle: All About The Drums\n\nStyle: Drum &amp; Bass\n\nLabel: Break-Fast Audio (BFADLP002)\n\nFormat: 320 kbps MP3\n\nRelease: 2012-09-24\n\ntime total: 02:02:05\n\nSize: 280 Mb\n\n\n\nTracklist:\n01. Amplicon - Rehabilitation (6:34)\n02. Reactiv - Brothers (6:13)\n03. Acid Lab - Red Dust (5:56)\n04. Resound &amp; Cyberworm - Initiation (6:24)\n05. Sativa &amp; NSF - Shadow In The Dark (6:01)\n06. Sub - Shinto (5:12)\n07. Fushara - Stealsign (6:44)\n08. Synapse - Uncertainty (6:26)\n09. Sativa, NSF &amp; Destroy2k - Doggone (6:14)\n10. Phuture-T - Quantum (7:31)\n11. Macc - Change &amp; Stay The Same (6:53)\n12. Sativa &amp; NSF - The Serengeti Stroke (6:34)\n13. Sub - Steganographie (7:27)\n14. Nic TVG - On The Plus Side (5:27)\n15. Sativa, NSF, Destroy2k &amp; Sickhead - Save Our Souls (6:21)\n16. Synapse - Shambhala (6:48)\n17. Amplicon - Triangular Funk (5:25)\n18. Sub - Memento Mori (6:53)\n19. NSF &amp; Sick &amp; Destroy - Flyin Fist Of Fear (7:02)","torrent":{"xt":"urn:btih:32cc8ecffb4851d0c5f7c65033f183e97fe6fc8c","amp;dn":"VA+-+All+About+The+Drums+%282012%29","amp;tr":["udp%3A%2F%2Ftracker.openbittorrent.com%3A80","udp%3A%2F%2Fopen.demonii.com%3A1337","udp%3A%2F%2Ftracker.coppersurfer.tk%3A6969","udp%3A%2F%2Fexodus.desync.com%3A6969"],"infoHash":"32cc8ecffb4851d0c5f7c65033f183e97fe6fc8c","infoHashBuffer":{"type":"Buffer","data":[50,204,142,207,251,72,81,208,197,247,198,80,51,241,131,233,127,230,252,140]},"announce":[],"urlList":[]}}