{"title":"Saskatoon Star-Phoenix, July 22 2013","uid":8724647,"size":3777363,"categoryP":"other","categoryS":"e_books","magnet":"?xt=urn:btih:351d70b4182d084945be05b2a3489aacc54f4812&amp;dn=Saskatoon+Star-Phoenix%2C+July+22+2013&amp;tr=udp%3A%2F%2Ftracker.openbittorrent.com%3A80&amp;tr=udp%3A%2F%2Fopen.demonii.com%3A1337&amp;tr=udp%3A%2F%2Ftracker.coppersurfer.tk%3A6969&amp;tr=udp%3A%2F%2Fexodus.desync.com%3A6969","seeders":1,"leechers":0,"uploader":"OrajelJunkie","files":-1,"time":1374491139,"description":"Saskatoon Star-Phoenix\nJuly 22 2013\nSaskatoon,Saskatchewan CA\n\n\nCreated by Calibre","torrent":{"xt":"urn:btih:351d70b4182d084945be05b2a3489aacc54f4812","amp;dn":"Saskatoon+Star-Phoenix%2C+July+22+2013","amp;tr":["udp%3A%2F%2Ftracker.openbittorrent.com%3A80","udp%3A%2F%2Fopen.demonii.com%3A1337","udp%3A%2F%2Ftracker.coppersurfer.tk%3A6969","udp%3A%2F%2Fexodus.desync.com%3A6969"],"infoHash":"351d70b4182d084945be05b2a3489aacc54f4812","infoHashBuffer":{"type":"Buffer","data":[53,29,112,180,24,45,8,73,69,190,5,178,163,72,154,172,197,79,72,18]},"announce":[],"urlList":[]}}