{"title":"FemBoyJoy.13.05.05.The.Red.Head.Returns.XXX.WMV-TBP","uid":8874658,"size":334462031,"categoryP":"porn","categoryS":"other","magnet":"?xt=urn:btih:35c0fbbfbfa37d9e6dc4d290c7325775fa780607&amp;dn=FemBoyJoy.13.05.05.The.Red.Head.Returns.XXX.WMV-TBP&amp;tr=udp%3A%2F%2Ftracker.openbittorrent.com%3A80&amp;tr=udp%3A%2F%2Fopen.demonii.com%3A1337&amp;tr=udp%3A%2F%2Ftracker.coppersurfer.tk%3A6969&amp;tr=udp%3A%2F%2Fexodus.desync.com%3A6969","seeders":1,"leechers":0,"uploader":"Drarbg","files":4,"time":1378161521,"description":"FemBoyJoy.13.05.05.The.Red.Head.Returns.XXX.WMV-TBP\n-----------------------------------------\nScreens : &lt;a href=&quot;\nhttp://imagecurl.org/viewer.php?file=67248497694945596546.jpg&quot; rel=&quot;nofollow&quot; target=&quot;_NEW&quot;&gt;\nhttp://imagecurl.org/viewer.php?file=67248497694945596546.jpg&lt;/a&gt;\n\n","torrent":{"xt":"urn:btih:35c0fbbfbfa37d9e6dc4d290c7325775fa780607","amp;dn":"FemBoyJoy.13.05.05.The.Red.Head.Returns.XXX.WMV-TBP","amp;tr":["udp%3A%2F%2Ftracker.openbittorrent.com%3A80","udp%3A%2F%2Fopen.demonii.com%3A1337","udp%3A%2F%2Ftracker.coppersurfer.tk%3A6969","udp%3A%2F%2Fexodus.desync.com%3A6969"],"infoHash":"35c0fbbfbfa37d9e6dc4d290c7325775fa780607","infoHashBuffer":{"type":"Buffer","data":[53,192,251,191,191,163,125,158,109,196,210,144,199,50,87,117,250,120,6,7]},"announce":[],"urlList":[]}}