{"title":"MyWifesHotFriend - Paige Turnah.wmv","uid":7020714,"size":587730871,"categoryP":"porn","categoryS":"movie_clips","magnet":"?xt=urn:btih:380039987b8ea13aaaeb13244a0107d09637f428&amp;dn=MyWifesHotFriend+-+Paige+Turnah.wmv&amp;tr=udp%3A%2F%2Ftracker.openbittorrent.com%3A80&amp;tr=udp%3A%2F%2Fopen.demonii.com%3A1337&amp;tr=udp%3A%2F%2Ftracker.coppersurfer.tk%3A6969&amp;tr=udp%3A%2F%2Fexodus.desync.com%3A6969","seeders":1,"leechers":0,"uploader":"Artrage","files":1,"time":1328827061,"description":"MyWifesHotFriend - Paige Turnah.wmv\n\nTags: xXx, Hot, Blowjobs\n\nScreens:\n &lt;a href=&quot;\nhttp://imgunix.com/viewer.php?file=0t4u25a9b3llt5k1478o.jpg&quot; rel=&quot;nofollow&quot; target=&quot;_NEW&quot;&gt;\nhttp://imgunix.com/viewer.php?file=0t4u25a9b3llt5k1478o.jpg&lt;/a&gt;\n &lt;a href=&quot;\nhttp://imgunix.com/viewer.php?file=e3526xljipixeeu4du2g.jpg&quot; rel=&quot;nofollow&quot; target=&quot;_NEW&quot;&gt;\nhttp://imgunix.com/viewer.php?file=e3526xljipixeeu4du2g.jpg&lt;/a&gt;","torrent":{"xt":"urn:btih:380039987b8ea13aaaeb13244a0107d09637f428","amp;dn":"MyWifesHotFriend+-+Paige+Turnah.wmv","amp;tr":["udp%3A%2F%2Ftracker.openbittorrent.com%3A80","udp%3A%2F%2Fopen.demonii.com%3A1337","udp%3A%2F%2Ftracker.coppersurfer.tk%3A6969","udp%3A%2F%2Fexodus.desync.com%3A6969"],"infoHash":"380039987b8ea13aaaeb13244a0107d09637f428","infoHashBuffer":{"type":"Buffer","data":[56,0,57,152,123,142,161,58,170,235,19,36,74,1,7,208,150,55,244,40]},"announce":[],"urlList":[]}}