{"title":"We.Live.Together.16.XXX.DVDRiP.XviD-DivXfacTory","uid":5992866,"size":2188070912,"categoryP":"porn","categoryS":"movies","magnet":"?xt=urn:btih:3c28d1fbf6a9a033fadc70be5d7d398e3a1cb704&amp;dn=We.Live.Together.16.XXX.DVDRiP.XviD-DivXfacTory&amp;tr=udp%3A%2F%2Ftracker.openbittorrent.com%3A80&amp;tr=udp%3A%2F%2Fopen.demonii.com%3A1337&amp;tr=udp%3A%2F%2Ftracker.coppersurfer.tk%3A6969&amp;tr=udp%3A%2F%2Fexodus.desync.com%3A6969","seeders":1,"leechers":4,"uploader":"kelvin09","files":3,"time":1290951025,"description":"Cover\n &lt;a href=&quot;\nhttp://www.seedimage.com/show.php/1097_1.jpg.html&quot; rel=&quot;nofollow&quot; target=&quot;_NEW&quot;&gt;\nhttp://www.seedimage.com/show.php/1097_1.jpg.html&lt;/a&gt;\n\n\nScreens\n &lt;a href=&quot;\nhttp://www.seedimage.com/show.php/1096_2.jpg.html&quot; rel=&quot;nofollow&quot; target=&quot;_NEW&quot;&gt;\nhttp://www.seedimage.com/show.php/1096_2.jpg.html&lt;/a&gt;\n\n &lt;a href=&quot;\nhttp://www.seedimage.com/show.php/1095_3.jpg.html&quot; rel=&quot;nofollow&quot; target=&quot;_NEW&quot;&gt;\nhttp://www.seedimage.com/show.php/1095_3.jpg.html&lt;/a&gt;\n\n &lt;a href=&quot;\nhttp://www.seedimage.com/show.php/1094_4.jpg.html&quot; rel=&quot;nofollow&quot; target=&quot;_NEW&quot;&gt;\nhttp://www.seedimage.com/show.php/1094_4.jpg.html&lt;/a&gt;\n\n\nSammie Rhodes, Celeste Star, Veronica, Alyssa Reece, Karlie Montana, Nikki, Lux Kassidy, Jana Jordan, Franziska Facella, Jayden Cole, Renee, Clara G, Topanga Fox, Ricci\n\nFrom our girl friends at college to roommates and friends of friends - we go on the streets, bars, parties &amp; malls and we pick up the cutest girlie girls and invite them to come over and party in our apartment. Thanks for dropping in, hope you enjoy your visit!","torrent":{"xt":"urn:btih:3c28d1fbf6a9a033fadc70be5d7d398e3a1cb704","amp;dn":"We.Live.Together.16.XXX.DVDRiP.XviD-DivXfacTory","amp;tr":["udp%3A%2F%2Ftracker.openbittorrent.com%3A80","udp%3A%2F%2Fopen.demonii.com%3A1337","udp%3A%2F%2Ftracker.coppersurfer.tk%3A6969","udp%3A%2F%2Fexodus.desync.com%3A6969"],"infoHash":"3c28d1fbf6a9a033fadc70be5d7d398e3a1cb704","infoHashBuffer":{"type":"Buffer","data":[60,40,209,251,246,169,160,51,250,220,112,190,93,125,57,142,58,28,183,4]},"announce":[],"urlList":[]}}