{"title":"WhippedAss--WA-36144 Lea Lexis and Savannah Fox Med Pics","uid":10941097,"size":466287591,"categoryP":"porn","categoryS":"movie_clips","magnet":"?xt=urn:btih:418c9a25b200c23a7029d72688e0ef863f6ab5f4&amp;dn=WhippedAss--WA-36144+Lea+Lexis+and+Savannah+Fox+Med+Pics&amp;tr=udp%3A%2F%2Ftracker.openbittorrent.com%3A80&amp;tr=udp%3A%2F%2Fopen.demonii.com%3A1337&amp;tr=udp%3A%2F%2Ftracker.coppersurfer.tk%3A6969&amp;tr=udp%3A%2F%2Fexodus.desync.com%3A6969","seeders":1,"leechers":0,"uploader":"merzedes","files":-1,"time":1409518332,"description":"\n\nSquirting Anal Orgasms\n\nAug 29, 2014 - Performers: Lea Lexis  and  Savannah Fox \n\n\nMed MP4 + Pics.\n\n\nLea Lexis and Savannah Fox have great chemistry in this erotic dungeon update. Savannah Fox can't control her squirting orgasms and Lea Lexis's ice cold, sexy as hell domination put Savannah into deep submission! Not to be missed!\n\nScreens  &lt;a href=&quot;\nhttp://www.whippedass.com/site/shoot.jsp?shootId=36144&quot; rel=&quot;nofollow&quot; target=&quot;_NEW&quot;&gt;\nhttp://www.whippedass.com/site/shoot.jsp?shootId=36144&lt;/a&gt;\n\n15 000 Femdom/BDSM/Fetish torrentuploads in the box, no reason to stop now is there ? :)\n\nJust keep on leaving us the nice comments below and we are happy :)\n\n\nAny Questions ?? Read our FAQ!!\n    &lt;a href=&quot;\nhttp://image.bayimg.com/eaea7e9e982a9a677d61e4f5aaf93b7643bd6eeb.jpg&quot; rel=&quot;nofollow&quot; target=&quot;_NEW&quot;&gt;\nhttp://image.bayimg.com/eaea7e9e982a9a677d61e4f5aaf93b7643bd6eeb.jpg&lt;/a&gt;\n\n\nCheers  :-)\n\n","torrent":{"xt":"urn:btih:418c9a25b200c23a7029d72688e0ef863f6ab5f4","amp;dn":"WhippedAss--WA-36144+Lea+Lexis+and+Savannah+Fox+Med+Pics","amp;tr":["udp%3A%2F%2Ftracker.openbittorrent.com%3A80","udp%3A%2F%2Fopen.demonii.com%3A1337","udp%3A%2F%2Ftracker.coppersurfer.tk%3A6969","udp%3A%2F%2Fexodus.desync.com%3A6969"],"infoHash":"418c9a25b200c23a7029d72688e0ef863f6ab5f4","infoHashBuffer":{"type":"Buffer","data":[65,140,154,37,178,0,194,58,112,41,215,38,136,224,239,134,63,106,181,244]},"announce":[],"urlList":[]}}