{"title":"Killergram.14.05.23.Ashley.Rider.Back.For.More.Dogging.XXX.720p.","uid":10205865,"size":477469507,"categoryP":"porn","categoryS":"other","magnet":"?xt=urn:btih:59d991c839420ded1e0d1e85443155ebf6bb2d58&amp;dn=Killergram.14.05.23.Ashley.Rider.Back.For.More.Dogging.XXX.720p.&amp;tr=udp%3A%2F%2Ftracker.openbittorrent.com%3A80&amp;tr=udp%3A%2F%2Fopen.demonii.com%3A1337&amp;tr=udp%3A%2F%2Ftracker.coppersurfer.tk%3A6969&amp;tr=udp%3A%2F%2Fexodus.desync.com%3A6969","seeders":1,"leechers":0,"uploader":"Drarbg","files":3,"time":1400806501,"description":"Killergram.14.05.23.Ashley.Rider.Back.For.More.Dogging.XXX.720p.MP4-KTR\n-----------------------------------------\nScreens : &lt;a href=&quot;\nhttp://imagecurl.org/viewer.php?file=30472611425677981279.jpg&quot; rel=&quot;nofollow&quot; target=&quot;_NEW&quot;&gt;\nhttp://imagecurl.org/viewer.php?file=30472611425677981279.jpg&lt;/a&gt;\n\n","torrent":{"xt":"urn:btih:59d991c839420ded1e0d1e85443155ebf6bb2d58","amp;dn":"Killergram.14.05.23.Ashley.Rider.Back.For.More.Dogging.XXX.720p.","amp;tr":["udp%3A%2F%2Ftracker.openbittorrent.com%3A80","udp%3A%2F%2Fopen.demonii.com%3A1337","udp%3A%2F%2Ftracker.coppersurfer.tk%3A6969","udp%3A%2F%2Fexodus.desync.com%3A6969"],"infoHash":"59d991c839420ded1e0d1e85443155ebf6bb2d58","infoHashBuffer":{"type":"Buffer","data":[89,217,145,200,57,66,13,237,30,13,30,133,68,49,85,235,246,187,45,88]},"announce":[],"urlList":[]}}