{"title":"Superclasico.2011.720p.BluRay.x264.DTS-NoGrp","uid":10764962,"size":4830681017,"categoryP":"video","categoryS":"hd___movies","magnet":"?xt=urn:btih:68424ab75c6322bad0f7025da1b8ea924e5869cb&amp;dn=Superclasico.2011.720p.BluRay.x264.DTS-NoGrp&amp;tr=udp%3A%2F%2Ftracker.openbittorrent.com%3A80&amp;tr=udp%3A%2F%2Fopen.demonii.com%3A1337&amp;tr=udp%3A%2F%2Ftracker.coppersurfer.tk%3A6969&amp;tr=udp%3A%2F%2Fexodus.desync.com%3A6969","seeders":1,"leechers":1,"uploader":"Drarbg","files":2,"time":1407975850,"description":" &lt;a href=&quot;https://rarbg.com&quot; rel=&quot;nofollow&quot; target=&quot;_NEW&quot;&gt;https://rarbg.com&lt;/a&gt;\n\nSuperclasico.2011.720p.BluRay.x264.DTS-NoGrp\n\nAuto IMDB: &lt;a href=&quot;\nhttp://www.imdb.com/title/tt1609492/&quot; rel=&quot;nofollow&quot; target=&quot;_NEW&quot;&gt;\nhttp://www.imdb.com/title/tt1609492/&lt;/a&gt;\n\n-----------------------------------------\nScreens : &lt;a href=&quot;\nhttp://i.imgur.com/PCqcUhB.jpg&quot; rel=&quot;nofollow&quot; target=&quot;_NEW&quot;&gt;\nhttp://i.imgur.com/PCqcUhB.jpg&lt;/a&gt; &lt;a href=&quot;\nhttp://i.imgur.com/E303jog.jpg&quot; rel=&quot;nofollow&quot; target=&quot;_NEW&quot;&gt;\nhttp://i.imgur.com/E303jog.jpg&lt;/a&gt; &lt;a href=&quot;\nhttp://i.imgur.com/EmzhDcq.jpg&quot; rel=&quot;nofollow&quot; target=&quot;_NEW&quot;&gt;\nhttp://i.imgur.com/EmzhDcq.jpg&lt;/a&gt; &lt;a href=&quot;\nhttp://i.imgur.com/A78y6eW.jpg&quot; rel=&quot;nofollow&quot; target=&quot;_NEW&quot;&gt;\nhttp://i.imgur.com/A78y6eW.jpg&lt;/a&gt;\n\n-----------------------------------------\nAuto Media Info :\nVideo Format........: AVC\nCodec ID............: V_MPEG4/ISO/AVC\nLength..............: 1h37mn\nVideo...............: 1280x544 ( 24.000fps )\nBitrate.............: 4888Kbps\nAudio Format........: DTS\nCodec ID............: A_DTS\nBit rate mode.......: Constant\nBitrate.............: 1509Kbps\nChannel(s)..........: 6 channels\nMultiple audios.....: Yes\nEmbeded Subs........: Russian,Danish\n\n","torrent":{"xt":"urn:btih:68424ab75c6322bad0f7025da1b8ea924e5869cb","amp;dn":"Superclasico.2011.720p.BluRay.x264.DTS-NoGrp","amp;tr":["udp%3A%2F%2Ftracker.openbittorrent.com%3A80","udp%3A%2F%2Fopen.demonii.com%3A1337","udp%3A%2F%2Ftracker.coppersurfer.tk%3A6969","udp%3A%2F%2Fexodus.desync.com%3A6969"],"infoHash":"68424ab75c6322bad0f7025da1b8ea924e5869cb","infoHashBuffer":{"type":"Buffer","data":[104,66,74,183,92,99,34,186,208,247,2,93,161,184,234,146,78,88,105,203]},"announce":[],"urlList":[]}}