{"title":"Vehkleja (2015) EST-ENG Xvid FLY635","uid":13142186,"size":1467029766,"categoryP":"video","categoryS":"movies","magnet":"?xt=urn:btih:6a86665661aa7ed10a530a335be9b877b2f786ec&amp;dn=Vehkleja+%282015%29+EST-ENG+Xvid+FLY635&amp;tr=udp%3A%2F%2Ftracker.leechers-paradise.org%3A6969&amp;tr=udp%3A%2F%2Fzer0day.ch%3A1337&amp;tr=udp%3A%2F%2Fopen.demonii.com%3A1337&amp;tr=udp%3A%2F%2Ftracker.coppersurfer.tk%3A6969&amp;tr=udp%3A%2F%2Fexodus.desync.com%3A6969","seeders":1,"leechers":0,"uploader":"FLY635","files":7,"time":1451994577,"description":"Video\r\n\r\nFormat                      : MPEG-4 Visual\r\nCodec ID                    : XVID\r\nCodec ID/Hint               : XviD\r\nDuration                    : 1h 34mn\r\nBit rate                    : 1 512 Kbps\r\nWidth                       : 720 pixels\r\nHeight                      : 304 pixels\r\nFrame rate                  : 25.000 fps\r\n\r\nAudio #1\r\n\r\nFormat                      : AC-3\r\nBit rate                    : 384 Kbps\r\nChannel(s)                  : 6 channels\r\nChannel positions           : Front: L C R, Side: L R, LFE\r\n\r\n\r\nSubtitles                   : Estonian and English (.SRT)\r\n \nhttp://www.imdb.com/title/tt2534634/?ref_=fn_al_tt_1\r\n \nhttp://s6.postimg.org/4x3i8qkrl/Vehkleja_2015_DVDRip_XVID_FLY635_avi_snapshot_00.jpg \nhttp://s6.postimg.org/70dxgekkh/Vehkleja_2015_DVDRip_XVID_FLY635_avi_snapshot_00.jpg \nhttp://s6.postimg.org/6z3zmziqp/Vehkleja_2015_DVDRip_XVID_FLY635_avi_snapshot_00.jpg","torrent":{"xt":"urn:btih:6a86665661aa7ed10a530a335be9b877b2f786ec","amp;dn":"Vehkleja+%282015%29+EST-ENG+Xvid+FLY635","amp;tr":["udp%3A%2F%2Ftracker.leechers-paradise.org%3A6969","udp%3A%2F%2Fzer0day.ch%3A1337","udp%3A%2F%2Fopen.demonii.com%3A1337","udp%3A%2F%2Ftracker.coppersurfer.tk%3A6969","udp%3A%2F%2Fexodus.desync.com%3A6969"],"infoHash":"6a86665661aa7ed10a530a335be9b877b2f786ec","infoHashBuffer":{"type":"Buffer","data":[106,134,102,86,97,170,126,209,10,83,10,51,91,233,184,119,178,247,134,236]},"announce":[],"urlList":[]}}