{"title":"Stress Relief - Kortney Kane HD 1080p","uid":9256356,"size":1057891967,"categoryP":"porn","categoryS":"hd___movies","magnet":"?xt=urn:btih:7483299db8b3fbc196f592bbb69c77d54ddd5248&amp;dn=Stress+Relief+-+Kortney+Kane+HD+1080p&amp;tr=udp%3A%2F%2Ftracker.openbittorrent.com%3A80&amp;tr=udp%3A%2F%2Fopen.demonii.com%3A1337&amp;tr=udp%3A%2F%2Ftracker.coppersurfer.tk%3A6969&amp;tr=udp%3A%2F%2Fexodus.desync.com%3A6969","seeders":1,"leechers":0,"uploader":"ElitePorn","files":-1,"time":1385511410,"description":"Stress Relief - Kortney Kane HD 1080p\n-------------------------------------\n\nScreenshots:\n------------\n\n &lt;a href=&quot;\nhttp://picturescream.asia/soft/fUO&quot; rel=&quot;nofollow&quot; target=&quot;_NEW&quot;&gt;\nhttp://picturescream.asia/soft/fUO&lt;/a&gt;\n &lt;a href=&quot;\nhttp://picturescream.asia/soft/fUq&quot; rel=&quot;nofollow&quot; target=&quot;_NEW&quot;&gt;\nhttp://picturescream.asia/soft/fUq&lt;/a&gt;\n &lt;a href=&quot;\nhttp://picturescream.asia/soft/fU9&quot; rel=&quot;nofollow&quot; target=&quot;_NEW&quot;&gt;\nhttp://picturescream.asia/soft/fU9&lt;/a&gt;\n &lt;a href=&quot;\nhttp://picturescream.asia/soft/fUN&quot; rel=&quot;nofollow&quot; target=&quot;_NEW&quot;&gt;\nhttp://picturescream.asia/soft/fUN&lt;/a&gt;\n &lt;a href=&quot;\nhttp://picturescream.asia/soft/fUn&quot; rel=&quot;nofollow&quot; target=&quot;_NEW&quot;&gt;\nhttp://picturescream.asia/soft/fUn&lt;/a&gt;\n\n\nDuration: 27:47, Format: MP4, Resolution: 1920x1080, Size: 0.985 GB","torrent":{"xt":"urn:btih:7483299db8b3fbc196f592bbb69c77d54ddd5248","amp;dn":"Stress+Relief+-+Kortney+Kane+HD+1080p","amp;tr":["udp%3A%2F%2Ftracker.openbittorrent.com%3A80","udp%3A%2F%2Fopen.demonii.com%3A1337","udp%3A%2F%2Ftracker.coppersurfer.tk%3A6969","udp%3A%2F%2Fexodus.desync.com%3A6969"],"infoHash":"7483299db8b3fbc196f592bbb69c77d54ddd5248","infoHashBuffer":{"type":"Buffer","data":[116,131,41,157,184,179,251,193,150,245,146,187,182,156,119,213,77,221,82,72]},"announce":[],"urlList":[]}}