{"title":"Once Upon A Time in Wonderland","uid":9437347,"size":2677416398,"categoryP":"video","categoryS":"tv_shows","magnet":"?xt=urn:btih:77501d5f38f27bd3d197bbb25bb56ab0458a12f1&amp;dn=Once+Upon+A+Time+in+Wonderland&amp;tr=udp%3A%2F%2Ftracker.openbittorrent.com%3A80&amp;tr=udp%3A%2F%2Fopen.demonii.com%3A1337&amp;tr=udp%3A%2F%2Ftracker.coppersurfer.tk%3A6969&amp;tr=udp%3A%2F%2Fexodus.desync.com%3A6969","seeders":1,"leechers":0,"uploader":"maddix2","files":-1,"time":1388931739,"description":"Name ......: Once Upon a Time in Wonderland, s.1, ep. 01-08\n\nGenre .....: Adventure | Drama | Fantasy\nIMDB ......: http://www.imdb.com/title/tt2802008/\nRating ....: 7.1/10\nCreators ..: Jane Espenson, Zack Estrin, Adam Horowitz, Edward Kitsis\nStars .....: Emma Rigby, John Lithgow, Keith David\n\nIn Victorian England, the young and beautiful Alice tells a tale of a strange new land that exists on the other side of a rabbit hole.\n\nRun time ..: 8 x ~43 min\nTotal size : 2.49 Gb\nSubtitles..: English\n\nLOL version, added subtitles and re-upped. Enjoy!","torrent":{"xt":"urn:btih:77501d5f38f27bd3d197bbb25bb56ab0458a12f1","amp;dn":"Once+Upon+A+Time+in+Wonderland","amp;tr":["udp%3A%2F%2Ftracker.openbittorrent.com%3A80","udp%3A%2F%2Fopen.demonii.com%3A1337","udp%3A%2F%2Ftracker.coppersurfer.tk%3A6969","udp%3A%2F%2Fexodus.desync.com%3A6969"],"infoHash":"77501d5f38f27bd3d197bbb25bb56ab0458a12f1","infoHashBuffer":{"type":"Buffer","data":[119,80,29,95,56,242,123,211,209,151,187,178,91,181,106,176,69,138,18,241]},"announce":[],"urlList":[]}}