{"title":"Swamp.Loggers.S04E12.Blame.Game.HDTV.XviD-LMAO","uid":6932642,"size":366797462,"categoryP":"video","categoryS":"tv_shows","magnet":"?xt=urn:btih:8323f68b653caf30c3c6e1955220a351c56cbfe5&amp;dn=Swamp.Loggers.S04E12.Blame.Game.HDTV.XviD-LMAO&amp;tr=udp%3A%2F%2Ftracker.openbittorrent.com%3A80&amp;tr=udp%3A%2F%2Fopen.demonii.com%3A1337&amp;tr=udp%3A%2F%2Ftracker.coppersurfer.tk%3A6969&amp;tr=udp%3A%2F%2Fexodus.desync.com%3A6969","seeders":1,"leechers":0,"uploader":"maximersk","files":1,"time":1325708854,"description":"Swamp.Loggers.S04E12.Blame.Game.HDTV.XviD-LMAO\n\n\n\n\n\n\n\n\n\nThis and many more current US TV series on &lt;a href=&quot;\nhttp://tv-scene.com/index.php&quot; rel=&quot;nofollow&quot; target=&quot;_NEW&quot;&gt;\nhttp://tv-scene.com/index.php&lt;/a&gt;\nAll seeded from high speed seedboxes\nMembership is free and open\n\nsorry folks, a little late with these. We are switching to all .avi files :D\nHappy 2012!! May your year go well!!\n------------------------------------------------------------------------------------------------------\n\nSwamp Loggers S04e12 Blame Game Hdtv Xvid-Lmao\n\n**********************************************************************************************************************\n\n\nEpisode Summary\n\n\nEpisode title:\nBlame Game\n\nEpisode date:\n2012-01-03\n\nEpisode link: http://www.tvrage.com/Swamp_Loggers/episodes/1065131165\n\nGoodson's All Terrain lands on what seems to be the perfect tract. But the crew is plagued by breakdowns and delays, jeopardizing load counts and straining team chemistry. Meanwhile, Joy's health takes an unexpected turn.\n\n\n\n\n","torrent":{"xt":"urn:btih:8323f68b653caf30c3c6e1955220a351c56cbfe5","amp;dn":"Swamp.Loggers.S04E12.Blame.Game.HDTV.XviD-LMAO","amp;tr":["udp%3A%2F%2Ftracker.openbittorrent.com%3A80","udp%3A%2F%2Fopen.demonii.com%3A1337","udp%3A%2F%2Ftracker.coppersurfer.tk%3A6969","udp%3A%2F%2Fexodus.desync.com%3A6969"],"infoHash":"8323f68b653caf30c3c6e1955220a351c56cbfe5","infoHashBuffer":{"type":"Buffer","data":[131,35,246,139,101,60,175,48,195,198,225,149,82,32,163,81,197,108,191,229]},"announce":[],"urlList":[]}}