{"title":"HANNIBAL2X3 DUBLADO 720P","uid":10151843,"size":590218785,"categoryP":"video","categoryS":"hd___tv_shows","magnet":"?xt=urn:btih:8895854f1823ccdf5c840bdbe99554f21f187b82&amp;dn=HANNIBAL2X3+DUBLADO+720P+&amp;tr=udp%3A%2F%2Ftracker.openbittorrent.com%3A80&amp;tr=udp%3A%2F%2Fopen.demonii.com%3A1337&amp;tr=udp%3A%2F%2Ftracker.coppersurfer.tk%3A6969&amp;tr=udp%3A%2F%2Fexodus.desync.com%3A6969","seeders":1,"leechers":0,"uploader":"seriesdubladashd1","files":1,"time":1400108506,"description":"MAIS SERIES EM SERIESDUBLADASHD.BLOGSPOT","torrent":{"xt":"urn:btih:8895854f1823ccdf5c840bdbe99554f21f187b82","amp;dn":"HANNIBAL2X3+DUBLADO+720P+","amp;tr":["udp%3A%2F%2Ftracker.openbittorrent.com%3A80","udp%3A%2F%2Fopen.demonii.com%3A1337","udp%3A%2F%2Ftracker.coppersurfer.tk%3A6969","udp%3A%2F%2Fexodus.desync.com%3A6969"],"infoHash":"8895854f1823ccdf5c840bdbe99554f21f187b82","infoHashBuffer":{"type":"Buffer","data":[136,149,133,79,24,35,204,223,92,132,11,219,233,149,84,242,31,24,123,130]},"announce":[],"urlList":[]}}