{"title":"Fire And Ice 2008 DVDRip XviD AC3-TBO(No Rars)","uid":4594601,"size":1468444554,"categoryP":"video","categoryS":"movies","magnet":"?xt=urn:btih:98b8b0f8769bd9e0a0f73b7de2611665eaba5dce&amp;dn=Fire+And+Ice+2008+DVDRip+XviD+AC3-TBO%28No+Rars%29&amp;tr=udp%3A%2F%2Ftracker.openbittorrent.com%3A80&amp;tr=udp%3A%2F%2Fopen.demonii.com%3A1337&amp;tr=udp%3A%2F%2Ftracker.coppersurfer.tk%3A6969&amp;tr=udp%3A%2F%2Fexodus.desync.com%3A6969","seeders":1,"leechers":0,"uploader":"cgaurav007","files":-1,"time":1229961035,"description":"IIIIIIIIIIIIIIIIIIIIIIIIIIIIIIIIIIIIIIIIIIIIIIIIIIIIIIIIIIIIIIIIIIIIIIIIIIIIIIIIII\nII                                                                   \nII     TTTTTTTTTTTTTTTTTTTTTTT BBBBBBBBBBBBBBBBB         OOOOOOOOO\nII     T:::::::::::::::::::::T B::::::::::::::::B      OO:::::::::OO\nII     T:::::::::::::::::::::T B::::::BBBBBB:::::B   OO:::::::::::::OO\nII     T:::::TT:::::::TT:::::T BB:::::B     B:::::B O:::::::OOO:::::::O\nII     TTTTTT  T:::::T  TTTTTT   B::::B     B:::::B O::::::O   O::::::O\nII             T:::::T           B::::B     B:::::B O:::::O     O:::::O\nII             T:::::T           B::::BBBBBB:::::B  O:::::O     O:::::O\nII             T:::::T           B:::::::::::::BB   O:::::O     O:::::O\nII             T:::::T           B::::BBBBBB:::::B  O:::::O     O:::::O\nII             T:::::T           B::::B     B:::::B O:::::O     O:::::O\nII             T:::::T           B::::B     B:::::B O:::::O     O:::::O\nII             T:::::T           B::::B     B:::::B O::::::O   O::::::O\nII           TT:::::::TT       BB:::::BBBBBB::::::B O:::::::OOO:::::::O\nII           T:::::::::T       B:::::::::::::::::B   OO:::::::::::::OO\nII           T:::::::::T       B::::::::::::::::B      OO:::::::::OO\nII           TTTTTTTTTTT       BBBBBBBBBBBBBBBBB        OOOOOOOOO       II\nII  \nII*******************************************************************************\nII                      Fire &amp; Ice: The Dragon Chronicles         \nII*******************************************************************************\nII \nII Genre\t    : Adventure | Fantasy | Drama\nII Year\t\t    : 2008\nII Country\t    : USA  | Romania\nII Release Date\t    : 21.12.2008\nII Runtime\t    : 01:25:52\nII Audio\t    : English\nII Language:        : English\nII IMDB\t\t    : http://www.imdb.com/title/tt1135493\nII \nII*******************************************************************************\nII\nII Complete name    : Fire.And.Ice.2008.DVDRip.XviD.AC3-TBO\nII Source           : R3 DVD5, NTSC, 16:9\nII Size             : 1400MB (1468299264 bytes)\nII Codec            : XviD\nII Video resolution : 704 x 400\nII Video bitrate    : 1889 Kbps\nII Audio codec      : Dolby AC3, 48000Hz, stereo, 384Kbps, 2 ch\nII FPS \t\t    : 23.98\nII \nII*******************************************************************************\nII                                                                                  \nII\t\t\t       enjoy by TBO team ;)\nII\nII*******************************************************************************\nII                               Screenshots:\nII \nII           &lt;a href=&quot; http://store.picbg.net/pubpic/31/5C/4c3276f31ec0315c.jpg&quot; rel=&quot;nofollow&quot; target=&quot;_NEW&quot;&gt; http://store.picbg.net/pubpic/31/5C/4c3276f31ec0315c.jpg&lt;/a&gt;\nII \nII           &lt;a href=&quot; http://store.picbg.net/pubpic/82/C0/7af7c3df37e282c0.jpg&quot; rel=&quot;nofollow&quot; target=&quot;_NEW&quot;&gt; http://store.picbg.net/pubpic/82/C0/7af7c3df37e282c0.jpg&lt;/a&gt;\nII \nII           &lt;a href=&quot; http://store.picbg.net/pubpic/6A/1C/a3b87e343c0a6a1c.jpg&quot; rel=&quot;nofollow&quot; target=&quot;_NEW&quot;&gt; http://store.picbg.net/pubpic/6A/1C/a3b87e343c0a6a1c.jpg&lt;/a&gt;\nII \n*******************************************************************************","torrent":{"xt":"urn:btih:98b8b0f8769bd9e0a0f73b7de2611665eaba5dce","amp;dn":"Fire+And+Ice+2008+DVDRip+XviD+AC3-TBO%28No+Rars%29","amp;tr":["udp%3A%2F%2Ftracker.openbittorrent.com%3A80","udp%3A%2F%2Fopen.demonii.com%3A1337","udp%3A%2F%2Ftracker.coppersurfer.tk%3A6969","udp%3A%2F%2Fexodus.desync.com%3A6969"],"infoHash":"98b8b0f8769bd9e0a0f73b7de2611665eaba5dce","infoHashBuffer":{"type":"Buffer","data":[152,184,176,248,118,155,217,224,160,247,59,125,226,97,22,101,234,186,93,206]},"announce":[],"urlList":[]}}