{"title":"[HardX] Isabella De Santos (Hot Anal Latina)","uid":11788201,"size":326245460,"categoryP":"porn","categoryS":"movie_clips","magnet":"?xt=urn:btih:ab67006a5575798848d2ac21761e35fbd5367e4d&amp;dn=%5BHardX%5D+Isabella+De+Santos+%28Hot+Anal+Latina%29&amp;tr=udp%3A%2F%2Ftracker.openbittorrent.com%3A80&amp;tr=udp%3A%2F%2Fopen.demonii.com%3A1337&amp;tr=udp%3A%2F%2Ftracker.coppersurfer.tk%3A6969&amp;tr=udp%3A%2F%2Fexodus.desync.com%3A6969","seeders":1,"leechers":0,"uploader":"Upl0ad3rR","files":1,"time":1427833732,"description":"---:More From My Torrent's Here:---   &lt;a href=&quot;\nhttps://thepiratebay.se/user/Upl0ad3rR&quot; rel=&quot;nofollow&quot; target=&quot;_NEW&quot;&gt;\nhttps://thepiratebay.se/user/Upl0ad3rR&lt;/a&gt;\n\n---:ScreeNshotS:---  &lt;a href=&quot;\nhttp://image-tpb.com/img-551ae7865e358.html&quot; rel=&quot;nofollow&quot; target=&quot;_NEW&quot;&gt;\nhttp://image-tpb.com/img-551ae7865e358.html&lt;/a&gt; \n &lt;a href=&quot;\nhttp://image-tpb.com/img-551ae7873fc04.html&quot; rel=&quot;nofollow&quot; target=&quot;_NEW&quot;&gt;\nhttp://image-tpb.com/img-551ae7873fc04.html&lt;/a&gt; \n &lt;a href=&quot;\nhttp://image-tpb.com/img-551ae788bd9de.html&quot; rel=&quot;nofollow&quot; target=&quot;_NEW&quot;&gt;\nhttp://image-tpb.com/img-551ae788bd9de.html&lt;/a&gt; \n\nClassy and respectable senorita Isabella De Santos is feeling slutty today. So after some romantic cuddling with the elegant cavalier Manuel Ferrara they both engage in a passionate session of rectal love making. Beautifully shot, this idyllic scene shows us the Latina with the attractive gluteal muscles practicing sodomy in such a natural way as a bee pollinating a flower","torrent":{"xt":"urn:btih:ab67006a5575798848d2ac21761e35fbd5367e4d","amp;dn":"%5BHardX%5D+Isabella+De+Santos+%28Hot+Anal+Latina%29","amp;tr":["udp%3A%2F%2Ftracker.openbittorrent.com%3A80","udp%3A%2F%2Fopen.demonii.com%3A1337","udp%3A%2F%2Ftracker.coppersurfer.tk%3A6969","udp%3A%2F%2Fexodus.desync.com%3A6969"],"infoHash":"ab67006a5575798848d2ac21761e35fbd5367e4d","infoHashBuffer":{"type":"Buffer","data":[171,103,0,106,85,117,121,136,72,210,172,33,118,30,53,251,213,54,126,77]},"announce":[],"urlList":[]}}