{"title":"[SheMaleStrokers] Felipa Lins - Smokin Brazilian Trans Girl Want","uid":14463144,"size":907708268,"categoryP":"porn","categoryS":"hd___movies","magnet":"?xt=urn:btih:b2ac10bc457d5f1cef1522414d70255441f68cc6&amp;dn=%5BSheMaleStrokers%5D+Felipa+Lins+-+Smokin+Brazilian+Trans+Girl+Want&amp;tr=udp%3A%2F%2Ftracker.leechers-paradise.org%3A6969&amp;tr=udp%3A%2F%2Fzer0day.ch%3A1337&amp;tr=udp%3A%2F%2Fopen.demonii.com%3A1337&amp;tr=udp%3A%2F%2Ftracker.coppersurfer.tk%3A6969&amp;tr=udp%3A%2F%2Fexodus.desync.com%3A6969","seeders":1,"leechers":2,"uploader":"KayWily","files":1,"time":1461829366,"description":"[SheMaleStrokers] Felipa Lins - Smokin Brazilian Trans Girl Wants to Squeeze Out A Wet One On You! (27 Apr 2016) \r\n\r\n  \nhttp://porn-harbor.com/image/NO7","torrent":{"xt":"urn:btih:b2ac10bc457d5f1cef1522414d70255441f68cc6","amp;dn":"%5BSheMaleStrokers%5D+Felipa+Lins+-+Smokin+Brazilian+Trans+Girl+Want","amp;tr":["udp%3A%2F%2Ftracker.leechers-paradise.org%3A6969","udp%3A%2F%2Fzer0day.ch%3A1337","udp%3A%2F%2Fopen.demonii.com%3A1337","udp%3A%2F%2Ftracker.coppersurfer.tk%3A6969","udp%3A%2F%2Fexodus.desync.com%3A6969"],"infoHash":"b2ac10bc457d5f1cef1522414d70255441f68cc6","infoHashBuffer":{"type":"Buffer","data":[178,172,16,188,69,125,95,28,239,21,34,65,77,112,37,84,65,246,140,198]},"announce":[],"urlList":[]}}