{"title":"[Passion-HD] Brooke Myers - Pussy Pillows (13.06.2016)","uid":14898346,"size":407166764,"categoryP":"porn","categoryS":"movie_clips","magnet":"?xt=urn:btih:ca3d1e12d4c05cbbdefdf92e088a44b96c3e3dbd&amp;dn=%5BPassion-HD%5D+Brooke+Myers+-+Pussy+Pillows+%2813.06.2016%29&amp;tr=udp%3A%2F%2Ftracker.leechers-paradise.org%3A6969&amp;tr=udp%3A%2F%2Fzer0day.ch%3A1337&amp;tr=udp%3A%2F%2Fopen.demonii.com%3A1337&amp;tr=udp%3A%2F%2Ftracker.coppersurfer.tk%3A6969&amp;tr=udp%3A%2F%2Fexodus.desync.com%3A6969","seeders":1,"leechers":0,"uploader":"KayWily","files":1,"time":1465795163,"description":"[Passion-HD] Brooke Myers - Pussy Pillows (13.06.2016)\r\n\r\n \nhttp://porn-harbor.com/image/NtV","torrent":{"xt":"urn:btih:ca3d1e12d4c05cbbdefdf92e088a44b96c3e3dbd","amp;dn":"%5BPassion-HD%5D+Brooke+Myers+-+Pussy+Pillows+%2813.06.2016%29","amp;tr":["udp%3A%2F%2Ftracker.leechers-paradise.org%3A6969","udp%3A%2F%2Fzer0day.ch%3A1337","udp%3A%2F%2Fopen.demonii.com%3A1337","udp%3A%2F%2Ftracker.coppersurfer.tk%3A6969","udp%3A%2F%2Fexodus.desync.com%3A6969"],"infoHash":"ca3d1e12d4c05cbbdefdf92e088a44b96c3e3dbd","infoHashBuffer":{"type":"Buffer","data":[202,61,30,18,212,192,92,187,222,253,249,46,8,138,68,185,108,62,61,189]},"announce":[],"urlList":[]}}