{"title":"Mike.and.Molly.S01E02.First.Date.HDTV.XviD-FQM [TZ]","uid":5856682,"size":183760248,"categoryP":"video","categoryS":"tv_shows","magnet":"?xt=urn:btih:ca686b414b5d7e65e5d8c747fd3c811d767ac2c6&amp;dn=Mike.and.Molly.S01E02.First.Date.HDTV.XviD-FQM+%5BTZ%5D&amp;tr=udp%3A%2F%2Ftracker.openbittorrent.com%3A80&amp;tr=udp%3A%2F%2Fopen.demonii.com%3A1337&amp;tr=udp%3A%2F%2Ftracker.coppersurfer.tk%3A6969&amp;tr=udp%3A%2F%2Fexodus.desync.com%3A6969","seeders":1,"leechers":1,"uploader":"torrentzone","files":1,"time":1285646703,"description":"If you like this torrent, then come join HTTP://TORRENTZONE.NET - more stuff, faster speeds, and no fakes!\n\n-------------------------------------------------------------------------------------\n\nProudly Presents\n\nRelease Type: HDTV\nSeries: Mike and Molly\nGenre: Comedy\nEpisode: S01E02\nTitle: First Date\nProduction Code: 102\nOrig. Air Date: 27 Sep 2010\nRelease Date: 27 Sep 2010\nSource: 1080i HDTV\nVideo Format: XviD\nVideo Resolution: 624x352\nVideo Bitrate: 1072 kbps\nVideo Framerate: 23.976\nAudio Format: MP3 VBR\nAudio Bitrate: 161 kbps average\nAudio Sample Rate: 48 KHz\nLength: 19:40.221\nSize: 183,760,248\nPacks: 10*20MB = 175MB\nLink: http://www.cbs.com/primetime/mike_and_molly/\n\nSummary\n\nMolly gets a cold before the first date with Mike and\ndecides to take some cold medication to help her feel\nbetter, but it leads to disastrous results","torrent":{"xt":"urn:btih:ca686b414b5d7e65e5d8c747fd3c811d767ac2c6","amp;dn":"Mike.and.Molly.S01E02.First.Date.HDTV.XviD-FQM+%5BTZ%5D","amp;tr":["udp%3A%2F%2Ftracker.openbittorrent.com%3A80","udp%3A%2F%2Fopen.demonii.com%3A1337","udp%3A%2F%2Ftracker.coppersurfer.tk%3A6969","udp%3A%2F%2Fexodus.desync.com%3A6969"],"infoHash":"ca686b414b5d7e65e5d8c747fd3c811d767ac2c6","infoHashBuffer":{"type":"Buffer","data":[202,104,107,65,75,93,126,101,229,216,199,71,253,60,129,29,118,122,194,198]},"announce":[],"urlList":[]}}