{"title":"Serial Experiments Lain BD-716p [JP, EN, IT, FR, SPA, Latin SPA ","uid":11259047,"size":19614500111,"categoryP":"video","categoryS":"hd___tv_shows","magnet":"?xt=urn:btih:e4d224a6a3340e818e90d9b1b5d6b8ef48e91508&amp;dn=Serial+Experiments+Lain+BD-716p+%5BJP%2C+EN%2C+IT%2C+FR%2C+SPA%2C+Latin+SPA+&amp;tr=udp%3A%2F%2Ftracker.openbittorrent.com%3A80&amp;tr=udp%3A%2F%2Fopen.demonii.com%3A1337&amp;tr=udp%3A%2F%2Ftracker.coppersurfer.tk%3A6969&amp;tr=udp%3A%2F%2Fexodus.desync.com%3A6969","seeders":1,"leechers":2,"uploader":"darkj6","files":347,"time":1413940454,"description":" ______   _______  ______    ___   _      ___  --------|\n|      | |   _   ||    _ |  |   | | |    |   ||   |----|    \n|  _    ||  |_|  ||   | ||  |   |_| |    |   ||   |___ \n| | |   ||       ||   |_||_ |      _|    |   ||    _  |\n| |_|   ||       ||    __  ||     |_  ___|   ||   | | |\n|       ||   _   ||   |  | ||    _  ||       ||   |_| |\n|______| |__| |__||___|  |_||___| |_||_______||_______|\n                                                                      &lt;a href=&quot;\nhttps://thepiratebay.se/user/darkj6/&quot; rel=&quot;nofollow&quot; target=&quot;_NEW&quot;&gt;\nhttps://thepiratebay.se/user/darkj6/&lt;/a&gt;\n\nJoin ThePirateBay Forum:\n                                                                                               &lt;a href=&quot;\nhttps://forum.suprbay.org/member.php?action=register&amp;referrer=908&quot; rel=&quot;nofollow&quot; target=&quot;_NEW&quot;&gt;\nhttps://forum.suprbay.org/member.php?action=register&amp;referrer=908&lt;/a&gt;\n\n\n[0000] Serial Experiments Lain BD-716p [JP, EN, IT, FR, SPA, Latin SPA Dub] [SPA &amp; EN subs only]\n\nirc://irc.rizon.net/0000","torrent":{"xt":"urn:btih:e4d224a6a3340e818e90d9b1b5d6b8ef48e91508","amp;dn":"Serial+Experiments+Lain+BD-716p+%5BJP%2C+EN%2C+IT%2C+FR%2C+SPA%2C+Latin+SPA+","amp;tr":["udp%3A%2F%2Ftracker.openbittorrent.com%3A80","udp%3A%2F%2Fopen.demonii.com%3A1337","udp%3A%2F%2Ftracker.coppersurfer.tk%3A6969","udp%3A%2F%2Fexodus.desync.com%3A6969"],"infoHash":"e4d224a6a3340e818e90d9b1b5d6b8ef48e91508","infoHashBuffer":{"type":"Buffer","data":[228,210,36,166,163,52,14,129,142,144,217,177,181,214,184,239,72,233,21,8]},"announce":[],"urlList":[]}}