{"title":"Girls Got Cream 18yo Girl Henessy","uid":5354921,"size":567325714,"categoryP":"porn","categoryS":"movie_clips","magnet":"?xt=urn:btih:e96a0284526f9c5c69252cfd6f39e192b63a1ba9&amp;dn=Girls+Got+Cream+18yo+Girl+Henessy&amp;tr=udp%3A%2F%2Ftracker.openbittorrent.com%3A80&amp;tr=udp%3A%2F%2Fopen.demonii.com%3A1337&amp;tr=udp%3A%2F%2Ftracker.coppersurfer.tk%3A6969&amp;tr=udp%3A%2F%2Fexodus.desync.com%3A6969","seeders":1,"leechers":0,"uploader":"1.No.1","files":1,"time":1265903837,"description":"Format: wmv\nSize: 541 MB\nResolution: 960x540\nDuration: 00:23:56\n\nScreenshot:\n &lt;a href=&quot;\nhttp://www.pixsor.com/share-16AD_4B7444B3.html&quot; rel=&quot;nofollow&quot; target=&quot;_NEW&quot;&gt;\nhttp://www.pixsor.com/share-16AD_4B7444B3.html&lt;/a&gt;","torrent":{"xt":"urn:btih:e96a0284526f9c5c69252cfd6f39e192b63a1ba9","amp;dn":"Girls+Got+Cream+18yo+Girl+Henessy","amp;tr":["udp%3A%2F%2Ftracker.openbittorrent.com%3A80","udp%3A%2F%2Fopen.demonii.com%3A1337","udp%3A%2F%2Ftracker.coppersurfer.tk%3A6969","udp%3A%2F%2Fexodus.desync.com%3A6969"],"infoHash":"e96a0284526f9c5c69252cfd6f39e192b63a1ba9","infoHashBuffer":{"type":"Buffer","data":[233,106,2,132,82,111,156,92,105,37,44,253,111,57,225,146,182,58,27,169]},"announce":[],"urlList":[]}}