{"title":"America's Got Powers 04 (of 7|Image|2012|Dgtl-1920|K6DVR-Empire)","uid":8976041,"size":58047131,"categoryP":"other","categoryS":"comics","magnet":"?xt=urn:btih:fa93cd0d406d0ae1a82fa77827055ddd02c17e92&amp;dn=America%27s+Got+Powers+04+%28of+7%7CImage%7C2012%7CDgtl-1920%7CK6DVR-Empire%29&amp;tr=udp%3A%2F%2Ftracker.openbittorrent.com%3A80&amp;tr=udp%3A%2F%2Fopen.demonii.com%3A1337&amp;tr=udp%3A%2F%2Ftracker.coppersurfer.tk%3A6969&amp;tr=udp%3A%2F%2Fexodus.desync.com%3A6969","seeders":1,"leechers":0,"uploader":"gesserit","files":-1,"time":1380442192,"description":"\nDetails per &lt;a href=&quot; http://comicbookdb.com/issue.php?ID=263665&quot; rel=&quot;nofollow&quot; target=&quot;_NEW&quot;&gt; http://comicbookdb.com/issue.php?ID=263665&lt;/a&gt;\n\nAmerica's Got Powers (2012) - #4\nImage Comics\n\nWriter(s):         Bryan Hitch, Jonathan Ross\nPenciller(s):      Bryan Hitch\nInker(s):          Paul Neary, Michael Jason Paz - 'Muasond'\nColorist(s):       Paul Mounts\nLetterer(s):       Chris Eliopoulos\nEditor(s):         Jeff Mariotte\nCover Artist(s):   Bryan Hitch\n\nCover Date:        December 2012\nCover Price:       US $2.99\nIssue Tagline:     None\nFormat:            Color; Standard Comic Issue; 32 pages\n","torrent":{"xt":"urn:btih:fa93cd0d406d0ae1a82fa77827055ddd02c17e92","amp;dn":"America%27s+Got+Powers+04+%28of+7%7CImage%7C2012%7CDgtl-1920%7CK6DVR-Empire%29","amp;tr":["udp%3A%2F%2Ftracker.openbittorrent.com%3A80","udp%3A%2F%2Fopen.demonii.com%3A1337","udp%3A%2F%2Ftracker.coppersurfer.tk%3A6969","udp%3A%2F%2Fexodus.desync.com%3A6969"],"infoHash":"fa93cd0d406d0ae1a82fa77827055ddd02c17e92","infoHashBuffer":{"type":"Buffer","data":[250,147,205,13,64,109,10,225,168,47,167,120,39,5,93,221,2,193,126,146]},"announce":[],"urlList":[]}}